whatsappcloudapi/__init__.py
whatsappcloudapi/api_helper.py
whatsappcloudapi/configuration.py
whatsappcloudapi/whatsappcloudapi_client.py
whatsappcloudapi/controllers/__init__.py
whatsappcloudapi/controllers/base_controller.py
whatsappcloudapi/controllers/business_profiles_controller.py
whatsappcloudapi/controllers/media_controller.py
whatsappcloudapi/controllers/messages_controller.py
whatsappcloudapi/controllers/phone_numbers_controller.py
whatsappcloudapi/controllers/registration_controller.py
whatsappcloudapi/controllers/two_step_verification_controller.py
whatsappcloudapi/exceptions/__init__.py
whatsappcloudapi/exceptions/api_exception.py
whatsappcloudapi/http/__init__.py
whatsappcloudapi/http/http_call_back.py
whatsappcloudapi/http/http_method_enum.py
whatsappcloudapi/http/http_request.py
whatsappcloudapi/http/http_response.py
whatsappcloudapi/http/auth/__init__.py
whatsappcloudapi/http/auth/o_auth_2.py
whatsappcloudapi/models/__init__.py
whatsappcloudapi/models/action.py
whatsappcloudapi/models/address.py
whatsappcloudapi/models/audio.py
whatsappcloudapi/models/body.py
whatsappcloudapi/models/business_profile.py
whatsappcloudapi/models/button.py
whatsappcloudapi/models/button_parameter.py
whatsappcloudapi/models/button_parameter_type_enum.py
whatsappcloudapi/models/component.py
whatsappcloudapi/models/component_type_enum.py
whatsappcloudapi/models/contact.py
whatsappcloudapi/models/content_type_enum.py
whatsappcloudapi/models/currency.py
whatsappcloudapi/models/date_time_object.py
whatsappcloudapi/models/document.py
whatsappcloudapi/models/email_object.py
whatsappcloudapi/models/footer.py
whatsappcloudapi/models/get_business_profile_id_response.py
whatsappcloudapi/models/get_phone_number_by_id_response.py
whatsappcloudapi/models/header.py
whatsappcloudapi/models/header_type_enum.py
whatsappcloudapi/models/image.py
whatsappcloudapi/models/interactive.py
whatsappcloudapi/models/interactive_type_enum.py
whatsappcloudapi/models/language.py
sdksio_whatsapp_cloud_api_sdk-1.0.0.dist-info/LICENSE
sdksio_whatsapp_cloud_api_sdk-1.0.0.dist-info/METADATA
sdksio_whatsapp_cloud_api_sdk-1.0.0.dist-info/WHEEL
sdksio_whatsapp_cloud_api_sdk-1.0.0.dist-info/top_level.txt
sdksio_whatsapp_cloud_api_sdk-1.0.0.dist-info/RECORD
