Metadata-Version: 2.1
Name: sdksio-whatsapp-cloud-api-sdk
Version: 1.0.0
Summary: Use cloud-hosted version of the WhatsApp Business API to send and receive messages
Author-email: developer-sdksio <developer+sdksio@apimatic.io>
Project-URL: Documentation, https://www.apimatic.io/apidocs/whatsapp-api/v/1_0#/python
Keywords: whatsapp,messages,api,whatsapp-api,whatsapp-sdk,chat-sdk
Requires-Python: >=3.7
License-File: LICENSE
Requires-Dist: apimatic-core (~=0.2.0)
Requires-Dist: apimatic-core-interfaces (~=0.1.0)
Requires-Dist: apimatic-requests-client-adapter (~=0.1.0)
Requires-Dist: python-dateutil (~=2.8.1)
Requires-Dist: enum34 (>=1.1.10,~=1.1)
Provides-Extra: testutils
Requires-Dist: pytest (>=7.2.2) ; extra == 'testutils'
